jsonkit/__init__.py
jsonkit/async_jsonfile.py
jsonkit/codec.py
jsonkit/custom_types.py
jsonkit/jsonfile.py
py_jsonkit-0.1.0.dist-info/LICENSE
py_jsonkit-0.1.0.dist-info/METADATA
py_jsonkit-0.1.0.dist-info/WHEEL
py_jsonkit-0.1.0.dist-info/RECORD
