Metadata-Version: 2.1
Name: py-jsonkit
Version: 0.1.0
Summary: A library for enhanced JSON file handling with support for datetime and UUID objects, both synchronously and asynchronously.
Home-page: https://github.com/ayrun3412/JSONKit
License: MIT
Author: ayrun
Author-email: ayrun3412@gmail.com
Requires-Python: >=3.12,<4.0
Classifier: License :: OSI Approved :: MIT License
Classifier: Programming Language :: Python :: 3
Classifier: Programming Language :: Python :: 3.12
Requires-Dist: aiofiles (>=24.1.0,<25.0.0)
Requires-Dist: rich (>=13.8.1,<14.0.0)
Project-URL: Repository, https://github.com/ayrun3412/JSONKit
